{"cameraMode":{"drawMode":0,"name":"Shaded","section":"Shading Mode"},"sceneLighting":true,"audioPlay":false,"sceneViewState":{"m_AlwaysRefresh":false,"showFog":true,"showSkybox":true,"showFlares":true,"showImageEffects":true,"showParticleSystems":true,"showVisualEffectGraphs":true,"m_FxEnabled":true},"in2DMode":false,"pivot":{"x":3.839433193206787,"y":-0.9490232467651367,"z":2.2604198455810549},"rotation":{"x":-0.2671704888343811,"y":0.4346776604652405,"z":-0.13674601912498475,"w":-0.8491849303245544},"size":7.6963629722595219,"orthographic":false}